prompt_automation/__init__.py
prompt_automation/config.py
prompt_automation/errorlog.py
prompt_automation/hotkeys.py
prompt_automation/logger.py
prompt_automation/paste.py
prompt_automation/renderer.py
prompt_automation/shortcuts.py
prompt_automation/starred.py
prompt_automation/switch_mode.py
prompt_automation/types.py
prompt_automation/update.py
prompt_automation/updater.py
prompt_automation/utils.py
prompt_automation/cli/__init__.py
prompt_automation/cli/cli.py
prompt_automation/cli/dependencies.py
prompt_automation/cli/render.py
prompt_automation/cli/template_select.py
prompt_automation/cli/update.py
prompt_automation/gui/__init__.py
prompt_automation/gui/constants.py
prompt_automation/gui/controller.py
prompt_automation/gui/error_dialogs.py
prompt_automation/gui/file_append.py
prompt_automation/gui/fonts.py
prompt_automation/gui/gui.py
prompt_automation/gui/new_template_wizard.py
prompt_automation/gui/options_menu.py
prompt_automation/gui/review_window.py
prompt_automation/gui/template_selector.py
prompt_automation/gui/collector/__init__.py
prompt_automation/gui/collector/fonts.py
prompt_automation/gui/collector/overrides.py
prompt_automation/gui/collector/persistence.py
prompt_automation/gui/collector/prompts.py
prompt_automation/gui/collector/components/__init__.py
prompt_automation/gui/collector/components/formatting.py
prompt_automation/gui/collector/components/orchestrator.py
prompt_automation/gui/collector/components/ui.py
prompt_automation/gui/selector/__init__.py
prompt_automation/gui/selector/controller.py
prompt_automation/gui/selector/model.py
prompt_automation/gui/selector/service.py
prompt_automation/gui/selector/view.py
prompt_automation/gui/selector/view/__init__.py
prompt_automation/gui/selector/view/exclusions.py
prompt_automation/gui/selector/view/orchestrator.py
prompt_automation/gui/selector/view/overrides.py
prompt_automation/gui/selector/view/preview.py
prompt_automation/gui/single_window/__init__.py
prompt_automation-1.0.0.dist-info/licenses/LICENSE
prompt_automation-1.0.0.dist-info/METADATA
prompt_automation-1.0.0.dist-info/WHEEL
prompt_automation-1.0.0.dist-info/entry_points.txt
prompt_automation-1.0.0.dist-info/top_level.txt
prompt_automation-1.0.0.dist-info/RECORD
