Metadata-Version: 2.4
Name: prompt-automation
Version: 1.0.0
Summary: Keyboard-only smart prompt launcher
Author: prompt-automation
Requires-Python: >=3.11
License-File: LICENSE
Requires-Dist: pyperclip
Provides-Extra: windows
Requires-Dist: keyboard; extra == "windows"
Dynamic: license-file
